[
  {
    "id": 1,
    "name": "Inventory Manager",
    "description": "A mobile application for keeping track of store inventory",
    "image": "/image1.jpg",
    "category": "Web Development",
    "link": "https://yourprojectalpha.com",
    "featured": true
  },
  {
    "id": 2,
    "name": "UniTransit",
    "description": "A mobile-based university transport system for booking campus rides with real-time map integration",
    "image": "/image2.jpg",
    "category": "Mobile Development",
    "link": "https://yourprojectbeta.com",
    "featured": true
  },
  {
    "id": 3,
    "name": "Project Gamma",
    "description": "A social media platform for sharing ideas and connecting with others",
    "image": "/image3.jpg",
    "category": "Web Development",
    "link": "https://yourprojectgamma.com",
    "featured": false
  }
]
